LICENSE.txt
README.md
setup.cfg
setup.py
BadgeGenerator/BadgeGenerator.py
BadgeGenerator/__init__.py
BadgeGenerator.egg-info/PKG-INFO
BadgeGenerator.egg-info/SOURCES.txt
BadgeGenerator.egg-info/dependency_links.txt
BadgeGenerator.egg-info/top_level.txt